<?xml version="1.0" ?>
<!DOCTYPE PISI SYSTEM "https://www.pisilinux.org/projeler/pisi/pisi-spec.dtd">
<PISI>
    <Source>
        <Name>retdec</Name>
        <Homepage>https://retdec.com/</Homepage>
        <Packager>
            <Name>Blue Devil</Name>
            <Email>bluedevil@sctzine.com</Email>
        </Packager>
        <PartOf>programming.debug</PartOf>
        <License>MIT</License>
        <IsA>app:console</IsA>
        <IsA>library</IsA>
        <Summary>RetDec is a retargetable machine-code decompiler based on LLVM.</Summary>
        <Description>RetDec is an open-source retargetable machine-code decompiler based on LLVM. The supported file formats are ELF, PE, Mach-O, COFF, AR (archive), Intel HEX and raw machine code. Supported architectures are 32-bit: Intel x86, ARM, MIPS, PIC32, and PowerPC 64-bit: x86-64.</Description>
        <Archive sha1sum="8b61d0b64558f419b5510d03daa8dc78fb66a76e" type="targz">https://github.com/avast/retdec/archive/v3.3.tar.gz</Archive>
        <Archive sha1sum="f1a527961533a0afb4a20cd048e53a2eb86eace1" type="tarxz" target="retdec-3.3/retdec-support">https://github.com/avast/retdec-support/releases/download/2019-03-08/retdec-support_2019-03-08.tar.xz</Archive>
        <BuildDependencies>
            <Dependency>openssl-devel</Dependency>
            <Dependency>python3-devel</Dependency>
            <Dependency>zlib-devel</Dependency>
            <Dependency>valgrind</Dependency>
            <Dependency>cmake</Dependency>
            <Dependency>llvm</Dependency>
        </BuildDependencies>
        <Patches>
            <!-- To avoid sandbox exceptions i patched main CMakeLists file -->
            <Patch>SCT-retdec-CMakeLists.patch</Patch>
            <!-- To fix and disable libdwarf's rpath -->
            <Patch>SCT-libdwarf-CMakeLists.patch</Patch>
        </Patches>
    </Source>

    <Package>
        <Name>retdec</Name>
        <Summary>RetDec is a retargetable machine-code decompiler based on LLVM.</Summary>
        <RuntimeDependencies>
            <Dependency>openssl</Dependency>
            <Dependency>python3</Dependency>
            <Dependency>zlib</Dependency>
        </RuntimeDependencies>
        <Files>
            <!-- retdec executables -->
            <Path fileType="executable">/usr/bin/retdec-signature-from-library-creator.py</Path>
            <Path fileType="executable">/usr/bin/retdec-archive-decompiler.py</Path>
            <Path fileType="executable">/usr/bin/retdec-macho-extractor</Path>
            <Path fileType="executable">/usr/bin/retdec-decompiler.py</Path>
            <Path fileType="executable">/usr/bin/retdec-ar-extractor</Path>
            <Path fileType="executable">/usr/bin/retdec-unpacker.py</Path>
            <Path fileType="executable">/usr/bin/retdec-fileinfo.py</Path>
            <Path fileType="executable">/usr/bin/retdec-bin2llvmir</Path>
            <Path fileType="executable">/usr/bin/retdec-llvmir2hll</Path>
            <Path fileType="executable">/usr/bin/retdec-color-c.py</Path>
            <Path fileType="executable">/usr/bin/retdec-config.py</Path>
            <Path fileType="executable">/usr/bin/retdec-pat2yara</Path>
            <Path fileType="executable">/usr/bin/retdec-fileinfo</Path>
            <Path fileType="executable">/usr/bin/retdec-unpacker</Path>
            <Path fileType="executable">/usr/bin/retdec-utils.py</Path>
            <Path fileType="executable">/usr/bin/retdec-stacofin</Path>
            <Path fileType="executable">/usr/bin/retdec-idr2pat</Path>
            <Path fileType="executable">/usr/bin/retdec-bin2pat</Path>
            <Path fileType="executable">/usr/bin/retdec-config</Path>
            <Path fileType="executable">/usr/bin/retdec-getsig</Path>
            <Path fileType="executable">/usr/bin/retdec-yarac</Path>
            <!-- retdec libraries -->
            <Path fileType="library">/usr/lib/libretdec-libdwarf.so</Path>
            <Path fileType="library">/usr/lib/libretdec-libelf.so</Path>
            <!-- retdec data and doc files -->
            <Path fileType="doc">/usr/share/doc/retdec</Path>
            <Path fileType="data">/usr/share/retdec</Path>
        </Files>
    </Package>

    <History>
        <Update release="1">
            <Date>2020-02-27</Date>
            <Version>3.3</Version>
            <Comment>First pisi release.</Comment>
            <Name>Blue Devil</Name>
            <Email>bluedevil@sctzine.com</Email>
        </Update>
    </History>
</PISI>